Workbook

Sheet Grunddaten
B1: TCO & Business Case Kalkulator
B2: Business Engineering 2 – Vorlage für die Abgabe
B3: Blaue Zellen = Eure Eingaben. Schwarze Zellen = Formeln (nicht verändern).
B5: Projektinformationen
B7: Projektname
B8: Team / Gruppe
B9: Case-Beschreibung (1 Satz)
B10: Ideal Customer Profile (aus Semester 1)
B12: Kernannahmen
B13: Parameter | C13: Wert | D13: Einheit | E13: Hinweis
B14: Stundensatz (€/h) | C14: 100 | E14: Fiktiver Stundensatz für die Kalkulation
B15: Steuersatz (MwSt) | C15: 0.19 | E15: 19% in Deutschland
B16: Kalkulationszeitraum (Jahre) | C16: 3 | E16: Für die TCO-Projektion
B17: Hosting-Kosten pro Monat (€) | C17: 0 | E17: 0€ bei Free Tier (Vercel, Netlify)
B18: Domain-Kosten pro Jahr (€) | C18: 0 | E18: Typisch: 10-15€/Jahr
B19: Wartung: Stunden pro Monat | C19: 0 | E19: Geschätzt: Updates, Monitoring, Fixes
B20: Jährliche Feature-Requests (Stunden) | C20: 0 | E20: Geschätzt: Neue Wünsche des Auftraggebers
B21: Jährliche Security-Updates (Stunden) | C21: 0 | E21: Dependency-Updates, Patches

Sheet Entwicklungskosten
B1: Entwicklungskosten – Aus dem Kosten-Tagebuch
B2: Tragt hier eure tatsächlichen Stunden aus dem Kosten-Tagebuch ein.
B4: Kategorie | C4: Stunden | D4: Kosten | E4: Anteil
B5: Konzeption & Design | C5: 0 | D5: =C5*Grunddaten!C14 -> 0 | E5: =IF(C$14=0,0,C5/C$14) -> 0
B6: Recherche & Lernen (Framework, JS, TS) | C6: 0 | D6: =C6*Grunddaten!C14 -> 0 | E6: =IF(C$14=0,0,C6/C$14) -> 0
B7: Implementierung (Code schreiben) | C7: 0 | D7: =C7*Grunddaten!C14 -> 0 | E7: =IF(C$14=0,0,C7/C$14) -> 0
B8: Debugging & Fehlerbehebung | C8: 0 | D8: =C8*Grunddaten!C14 -> 0 | E8: =IF(C$14=0,0,C8/C$14) -> 0
B9: Testing & Qualitätssicherung | C9: 0 | D9: =C9*Grunddaten!C14 -> 0 | E9: =IF(C$14=0,0,C9/C$14) -> 0
B10: Dokumentation (README, ADRs, Business Case) | C10: 0 | D10: =C10*Grunddaten!C14 -> 0 | E10: =IF(C$14=0,0,C10/C$14) -> 0
B11: Setup & Konfiguration | C11: 0 | D11: =C11*Grunddaten!C14 -> 0 | E11: =IF(C$14=0,0,C11/C$14) -> 0
B12: Code Reviews & Peer Feedback | C12: 0 | D12: =C12*Grunddaten!C14 -> 0 | E12: =IF(C$14=0,0,C12/C$14) -> 0
B13: Präsentationsvorbereitung | C13: 0 | D13: =C13*Grunddaten!C14 -> 0 | E13: =IF(C$14=0,0,C13/C$14) -> 0
B14: GESAMT Entwicklungskosten | C14: =SUM(C5:C13) -> 0 | D14: =SUM(D5:D13) -> 0 | E14: 1
B17: Analyse
B18: Davon 'Lernkosten' (Recherche & Lernen + Setup) | D18: =D6+D11 -> 0
B19: Davon 'Produktivkosten' (Gesamt - Lernkosten) | D19: =D14-D18 -> 0
B20: Geschätzte Kosten beim 2. Projekt (ohne Lernkosten) | D20: =D19 -> 0

Sheet TCO Projektion
B1: Total Cost of Ownership – 3-Jahres-Projektion
B2: Alle laufenden Kosten über 3 Jahre. Entwicklungskosten werden aus Sheet 'Entwicklungskosten' übernommen.
B4: Kostenblock | C4: Jahr 1 | D4: Jahr 2 | E4: Jahr 3 | F4: Gesamt
B5: Entwicklung (einmalig) | C5: =Entwicklungskosten!D14 -> 0 | D5: =0 -> 0 | E5: =0 -> 0 | F5: =SUM(C5:E5) -> 0
B6: Hosting & Infrastruktur | C6: =Grunddaten!C17*12 -> 0 | D6: =Grunddaten!C17*12 -> 0 | E6: =Grunddaten!C17*12 -> 0 | F6: =SUM(C6:E6) -> 0
B7: Domain | C7: =Grunddaten!C18 -> 0 | D7: =Grunddaten!C18 -> 0 | E7: =Grunddaten!C18 -> 0 | F7: =SUM(C7:E7) -> 0
B8: Wartung & Updates | C8: =Grunddaten!C19*12*Grunddaten!C14 -> 0 | D8: =Grunddaten!C19*12*Grunddaten!C14 -> 0 | E8: =Grunddaten!C19*12*Grunddaten!C14 -> 0 | F8: =SUM(C8:E8) -> 0
B9: Feature-Requests | C9: =Grunddaten!C20*Grunddaten!C14 -> 0 | D9: =Grunddaten!C20*Grunddaten!C14*1.5 -> 0 | E9: =Grunddaten!C20*Grunddaten!C14*2 -> 0 | F9: =SUM(C9:E9) -> 0
B10: Security-Updates | C10: =Grunddaten!C21*Grunddaten!C14 -> 0 | D10: =Grunddaten!C21*Grunddaten!C14 -> 0 | E10: =Grunddaten!C21*Grunddaten!C14 -> 0 | F10: =SUM(C10:E10) -> 0
B11: GESAMT TCO | C11: =SUM(C5:C10) -> 0 | D11: =SUM(D5:D10) -> 0 | E11: =SUM(E5:E10) -> 0 | F11: =SUM(F5:F10) -> 0
B12: Davon: Anteil Entwicklung an TCO | F12: =C5/F11 -> #DIV/0!

Sheet Break-Even
B1: Break-Even-Analyse
B2: Ab wann verdient die Software ihr Investment zurück?
B4: Monatlicher Nutzen
B5: Nutzen-Typ | C5: Monatlicher Wert (€) | E5: Erklärung
B6: Zusätzliche Verkäufe / Umsatz | C6: 0 | E6: Nur bei E-Commerce Cases
B7: Zeitersparnis Mitarbeiter (Stunden × Stundensatz) | C7: 0 | E7: Internes Tool: Gesparte manuelle Arbeit
B8: Reduzierte Support-Anfragen | C8: 0 | E8: Weniger Anrufe/Mails durch Self-Service
B9: Lead-Generierung (Leads × Wert pro Lead) | C9: 0 | E9: Kontaktanfragen, Registrierungen
B10: Sonstiger messbarer Nutzen | C10: 0 | E10: Branchenspezifisch
B11: GESAMT Monatlicher Nutzen | C11: =SUM(C6:C10) -> 0
B13: Monatliche Kosten
B14: Monatliche Betriebskosten (aus TCO) | C14: =('TCO Projektion'!C11-'TCO Projektion'!C5)/12 -> 0
B16: Break-Even-Berechnung
B17: Entwicklungskosten (Investition) | C17: =Entwicklungskosten!D14 -> 0
B18: Monatlicher Nettonutzen (Nutzen - Kosten) | C18: =C11-C14 -> 0
B19: ★ Break-Even in Monaten | C19: =IF(C18<=0,"Nie",C17/C18) -> Nie
B21: Sensitivitätsanalyse
B22: Szenario | C22: Nutzen-Faktor | D22: Break-Even (Monate)
B23: Pessimistisch | C23: 0.5 | D23: =IF((C11*C23-C14)<=0,"Nie",C17/(C11*C23-C14)) -> Nie
B24: Base Case | C24: 1 | D24: =IF((C11*C24-C14)<=0,"Nie",C17/(C11*C24-C14)) -> Nie
B25: Optimistisch | C25: 2 | D25: =IF((C11*C25-C14)<=0,"Nie",C17/(C11*C25-C14)) -> Nie

Sheet SaaS Skalierung
B13: Anzahl Kunden | C13: Entwicklung (einmalig, verteilt) | D13: Setup-Kosten (kumuliert) | E13: Monatl. Umsatz | F13: Monatl. Support-Kosten | G13: Monatl. Infrastruktur | H13: Monatl. Gewinn | I13: Gesamt-Kosten pro Kunde
B14: 1 | C14: =Entwicklungskosten!D14/B14 -> 0 | D14: =(B14-1)*'SaaS Skalierung'!C7*Grunddaten!C14 -> 0 | E14: =B14*C6 -> 0 | F14: =B14*C8*Grunddaten!C14 -> 0 | G14: =B14*C9 -> 0 | H14: =E14-F14-G14 -> 0 | I14: =(Entwicklungskosten!D14+D14)/B14 -> 0
B15: 2 | C15: =Entwicklungskosten!D14/B15 -> 0 | D15: =(B15-1)*'SaaS Skalierung'!C7*Grunddaten!C14 -> 0 | E15: =B15*C6 -> 0 | F15: =B15*C8*Grunddaten!C14 -> 0 | G15: =B15*C9 -> 0 | H15: =E15-F15-G15 -> 0 | I15: =(Entwicklungskosten!D14+D15)/B15 -> 0
B16: 5 | C16: =Entwicklungskosten!D14/B16 -> 0 | D16: =(B16-1)*'SaaS Skalierung'!C7*Grunddaten!C14 -> 0 | E16: =B16*C6 -> 0 | F16: =B16*C8*Grunddaten!C14 -> 0 | G16: =B16*C9 -> 0 | H16: =E16-F16-G16 -> 0 | I16: =(Entwicklungskosten!D14+D16)/B16 -> 0
B17: 10 | C17: =Entwicklungskosten!D14/B17 -> 0 | D17: =(B17-1)*'SaaS Skalierung'!C7*Grunddaten!C14 -> 0 | E17: =B17*C6 -> 0 | F17: =B17*C8*Grunddaten!C14 -> 0 | G17: =B17*C9 -> 0 | H17: =E17-F17-G17 -> 0 | I17: =(Entwicklungskosten!D14+D17)/B17 -> 0
B18: 25 | C18: =Entwicklungskosten!D14/B18 -> 0 | D18: =(B18-1)*'SaaS Skalierung'!C7*Grunddaten!C14 -> 0 | E18: =B18*C6 -> 0 | F18: =B18*C8*Grunddaten!C14 -> 0 | G18: =B18*C9 -> 0 | H18: =E18-F18-G18 -> 0 | I18: =(Entwicklungskosten!D14+D18)/B18 -> 0
B19: 50 | C19: =Entwicklungskosten!D14/B19 -> 0 | D19: =(B19-1)*'SaaS Skalierung'!C7*Grunddaten!C14 -> 0 | E19: =B19*C6 -> 0 | F19: =B19*C8*Grunddaten!C14 -> 0 | G19: =B19*C9 -> 0 | H19: =E19-F19-G19 -> 0 | I19: =(Entwicklungskosten!D14+D19)/B19 -> 0
B20: 100 | C20: =Entwicklungskosten!D14/B20 -> 0 | D20: =(B20-1)*'SaaS Skalierung'!C7*Grunddaten!C14 -> 0 | E20: =B20*C6 -> 0 | F20: =B20*C8*Grunddaten!C14 -> 0 | G20: =B20*C9 -> 0 | H20: =E20-F20-G20 -> 0 | I20: =(Entwicklungskosten!D14+D20)/B20 -> 0
B22: Erkenntnis
B23: Die Grenzkosten sinken mit jedem Kunden. Das ist der fundamentale Vorteil digitaler Produkte:
B24: Software einmal entwickeln, beliebig oft verkaufen – ohne proportionalen Kostenanstieg.

Sheet Alternativenvergleich
B1: Alternativenvergleich – Opportunity Costs
B2: Was hätte der Auftraggeber stattdessen mit dem Budget machen können?
B4: Alternative | C4: Kosten Jahr 1 | D4: Kosten Jahr 2 | E4: Kosten Jahr 3 | F4: Kosten 3 Jahre
B5: Eure Custom-Lösung | C5: ='TCO Projektion'!C11 -> 0 | D5: ='TCO Projektion'!D11 -> 0 | E5: ='TCO Projektion'!E11 -> 0 | F5: =SUM(C5:E5) -> 0
B6: Shopify / Wix (Abo-Modell) | C6: 0 | D6: 0 | E6: 0 | F6: =SUM(C6:E6) -> 0
B7: WordPress + Premium Theme | C7: 0 | D7: 0 | E7: 0 | F7: =SUM(C7:E7) -> 0
B8: Agentur beauftragen | C8: 0 | D8: 0 | E8: 0 | F8: =SUM(C8:E8) -> 0
B9: Nichts tun (Status quo) | C9: 0 | D9: 0 | E9: 0 | F9: =SUM(C9:E9) -> 0
B11: Hinweis: Recherchiert realistische Kosten für die Alternativen.
B12: Shopify: ~30-300€/Monat. WordPress: ~500-2.000€ Setup + Hosting. Agentur: 80-150€/h.
B13: 'Nichts tun' hat auch Kosten: Verlorene Kunden, manuelle Prozesse, Wettbewerbsnachteil.
